{
  "reviews": [{
    "reviewer": {
      "displayName": "Raju Pal"
    },
    "starRating": "FIVE",
    "comment": "Great place to visit love the ambience and craft of cafe they served best food with Verity of beverages staff are so welcoming and polite casual dine in experience and loved it ❤️❤️❤️",
    "createTime": "2026-03-04T15:28:01.272709Z",
    "updateTime": "2026-03-04T15:28:01.272709Z",
    "reviewReply": {
      "comment": "Great to know you loved the vibe, the food, and the drinks. Happy to hear the team made you feel welcome. Hope to see you again soon.",
      "updateTime": "2026-03-09T10:43:05.168097Z"
    },
    "name": "accounts/100486096577551952970/locations/7132653567992557892/reviews/Ci9DQUlRQUNvZENodHljRjlvT25kelZGSkhWVWwwZUZKMFZEaHpSa1l4U1hWVlYxRRAB"
  }, {
    "reviewer": {
      "displayName": "Halima Shaikh"
    },
    "starRating": "FIVE",
    "comment": "The food here is very tasty, staff is very polite and helpful. Overall, it’s a really nice place and a great experience. 😊",
    "createTime": "2026-03-04T15:27:37.644221Z",
    "updateTime": "2026-03-04T15:27:37.644221Z",
    "reviewReply": {
      "comment": "Happy to hear the food and the service made your visit special. We look forward to hosting you again soon.",
      "updateTime": "2026-03-09T10:52:12.918649Z"
    },
    "name": "accounts/100486096577551952970/locations/7132653567992557892/reviews/Ci9DQUlRQUNvZENodHljRjlvT210SFdWRTRVV3BOUWw5bWRIcFBhblpxYTNGME1XYxAB"
  }, {
    "reviewer": {
      "displayName": "System Manager"
    },
    "starRating": "FIVE",
    "comment": "The food is very tasty and well prepared. The ambiance is also very nice and comfortable. The staff is very polite and helpful. Overall, it’s a really nice place and a great experience. 😊",
    "createTime": "2026-03-04T15:25:49.978356Z",
    "updateTime": "2026-03-04T15:25:49.978356Z",
    "reviewReply": {
      "comment": "Glad you enjoyed the ambience and the food. It’s great to know the service made your visit even better. Looking forward to welcoming you again soon.",
      "updateTime": "2026-03-09T10:52:42.488540Z"
    },
    "name": "accounts/100486096577551952970/locations/7132653567992557892/reviews/Ci9DQUlRQUNvZENodHljRjlvT2t0Q1NVdGhSSEJtU1dkd1pYWTVNRXhIY21reE9XYxAB"
  }, {
    "reviewer": {
      "displayName": "Vedant Patil"
    },
    "starRating": "FIVE",
    "comment": "I recently visited Coffee Island and had a great experience. The coffee tasted rich and fresh, the ambiance was cozy, and the staff was friendly. It’s definitely a nice place for coffee lovers.",
    "createTime": "2026-03-04T14:35:48.535854Z",
    "updateTime": "2026-03-04T14:35:48.535854Z",
    "reviewReply": {
      "comment": "Great to hear the coffee, ambience, and service left such a strong impression. We appreciate you taking the time to share this and hope to see you again soon.",
      "updateTime": "2026-03-09T10:53:05.999763Z"
    },
    "name": "accounts/100486096577551952970/locations/7132653567992557892/reviews/Ci9DQUlRQUNvZENodHljRjlvT210cGFrZGxVV3hDZDJoc1pucElTa3RqV1dSWFJHYxAB"
  }, {
    "reviewer": {
      "displayName": "jagruti karade"
    },
    "starRating": "FIVE",
    "comment": "Peaceful vibes, Good quality food, calm ambience, and respectful service. Thank you to Lavanya for his friendly and attentive service",
    "createTime": "2026-03-04T14:35:43.161793Z",
    "updateTime": "2026-03-04T14:35:43.161793Z",
    "reviewReply": {
      "comment": "Glad to hear you enjoyed the peaceful vibe, good food, and calm ambience. Glad the service made your visit even better. Looking forward to welcoming you again soon.",
      "updateTime": "2026-03-09T11:16:01.171402Z"
    },
    "name": "accounts/100486096577551952970/locations/7132653567992557892/reviews/Ci9DQUlRQUNvZENodHljRjlvT2t0dlRHNUJXbWhZV1hoelkyTkJja0pmZVZGaVdsRRAB"
  }, {
    "reviewer": {
      "displayName": "Jiya Pawar"
    },
    "starRating": "FIVE",
    "comment": "I had a great experience at Coffee Island. The coffee was excellent and the ambience was very comfortable. Special thanks to Lavanya for his polite and friendly service—he made our visit even more pleasant. 😊",
    "createTime": "2026-03-04T14:24:14.240338Z",
    "updateTime": "2026-03-04T14:24:14.240338Z",
    "reviewReply": {
      "comment": "Great to know the coffee and ambience made your experience special. Happy to hear the service added to it as well. Hope to see you again soon.",
      "updateTime": "2026-03-09T11:20:42.223542Z"
    },
    "name": "accounts/100486096577551952970/locations/7132653567992557892/reviews/Ci9DQUlRQUNvZENodHljRjlvT2tJeVpHMXJOMnBoY0RsdU5YSXhSM0YwUVZWblRFRRAB"
  }, {
    "reviewer": {
      "displayName": "Lavanya Patankar"
    },
    "starRating": "FIVE",
    "comment": "Got amazing breakfast, great taste , very wonderful staff, keep it up guys .. 👏",
    "createTime": "2026-03-04T13:52:11.654814Z",
    "updateTime": "2026-03-04T13:52:11.654814Z",
    "reviewReply": {
      "comment": "Happy to hear the breakfast, flavours, and warm service made your visit special. We look forward to hosting you again soon.",
      "updateTime": "2026-03-09T11:21:43.668559Z"
    },
    "name": "accounts/100486096577551952970/locations/7132653567992557892/reviews/Ci9DQUlRQUNvZENodHljRjlvT25sV2FHTTBVR3ROYjA4MVVHNXhRVzFrWmxwbmRHYxAB"
  }, {
    "reviewer": {
      "displayName": "Manthan"
    },
    "starRating": "FIVE",
    "comment": "Nice atmosphere Nice environment\nNice conversation with miss Gauri\nThanks",
    "createTime": "2026-03-04T11:23:35.532965Z",
    "updateTime": "2026-03-04T11:23:35.532965Z",
    "reviewReply": {
      "comment": "Great to hear you enjoyed the ambience and your visit. Hope to see you again soon.",
      "updateTime": "2026-03-09T11:22:23.206143Z"
    },
    "name": "accounts/100486096577551952970/locations/7132653567992557892/reviews/Ci9DQUlRQUNvZENodHljRjlvT21wdlpYZFpSMjFXYlRJdFExVTBYMHhJT1d4eFRuYxAB"
  }, {
    "reviewer": {
      "displayName": "Raj Chavan"
    },
    "starRating": "FIVE",
    "comment": "Excellent service\nFood was very good special the pasta\nThank you for suggestions miss Gauri and Lavanya",
    "createTime": "2026-03-04T11:20:07.152892Z",
    "updateTime": "2026-03-04T11:20:07.152892Z",
    "reviewReply": {
      "comment": "Happy to hear you enjoyed the food and the service. We look forward to hosting you again soon.",
      "updateTime": "2026-03-09T11:23:18.382536Z"
    },
    "name": "accounts/100486096577551952970/locations/7132653567992557892/reviews/Ci9DQUlRQUNvZENodHljRjlvT21Wek0xaEVTRFp4WkVkeldGZHNhbWhWYVdsSlRsRRAB"
  }, {
    "reviewer": {
      "displayName": "Nidhi Chauhan Rathod"
    },
    "starRating": "FIVE",
    "comment": "Its a really cool place to visit with fresh options available in drinks and food",
    "createTime": "2026-03-03T14:15:04.149504Z",
    "updateTime": "2026-03-03T14:15:04.149504Z",
    "name": "accounts/100486096577551952970/locations/7132653567992557892/reviews/Ci9DQUlRQUNvZENodHljRjlvT2poSGRHWnlUVUUzTlhWMFYya3pTVXBsVEZoUmJYYxAB"
  }, {
    "reviewer": {
      "displayName": "Sayoni Banerjee"
    },
    "starRating": "FIVE",
    "comment": "The overall expectation and experience was good. Food ia also good and fresh. Loved it",
    "createTime": "2026-03-03T12:57:44.583059Z",
    "updateTime": "2026-03-03T12:57:44.583059Z",
    "reviewReply": {
      "comment": "Happy to hear you had a good experience and enjoyed the food. We look forward to hosting you again soon.",
      "updateTime": "2026-03-09T11:24:01.676734Z"
    },
    "name": "accounts/100486096577551952970/locations/7132653567992557892/reviews/Ci9DQUlRQUNvZENodHljRjlvT2toWE1TMUVkakZNU2xrM2RqQlNVamhHY25FNVFuYxAB"
  }, {
    "reviewer": {
      "displayName": "Arkadeep Bal"
    },
    "starRating": "FIVE",
    "comment": "Both the coffee and the food were really good. Will definitely come back again!",
    "createTime": "2026-03-02T16:59:50.107426Z",
    "updateTime": "2026-03-02T16:59:50.107426Z",
    "reviewReply": {
      "comment": "Glad you enjoyed the coffee and the food. We look forward to hosting you again soon.",
      "updateTime": "2026-03-09T11:26:02.667314Z"
    },
    "name": "accounts/100486096577551952970/locations/7132653567992557892/reviews/Ci9DQUlRQUNvZENodHljRjlvT2s5c01XZHVhMGRzZFRrMWNHTXdUeTFLWDBkZldHYxAB"
  }, {
    "reviewer": {
      "displayName": "Sourabh Joshi"
    },
    "starRating": "FIVE",
    "comment": "Had an amazing experience here! The food was fresh, flavorful, and perfectly presented. Every dish had a great balance of taste and quality.\n\nThe coffee was rich, aromatic, and brewed just right – definitely a must-try for coffee lovers. ☕\n\nHighly recommended for a relaxing hangout!",
    "createTime": "2026-03-02T16:54:50.109798Z",
    "updateTime": "2026-03-02T16:54:50.109798Z",
    "reviewReply": {
      "comment": "Glad you enjoyed the coffee and the food. We look forward to hosting you again soon.",
      "updateTime": "2026-03-09T11:26:28.282097Z"
    },
    "name": "accounts/100486096577551952970/locations/7132653567992557892/reviews/Ci9DQUlRQUNvZENodHljRjlvT25ad2VXbzJRMTlDZVRoSGQzaDVVSGhNTW5oYVIxRRAB"
  }, {
    "reviewer": {
      "displayName": "Amrita Basu"
    },
    "starRating": "FIVE",
    "comment": "Very good food and service",
    "createTime": "2026-03-02T16:50:42.847312Z",
    "updateTime": "2026-03-02T16:50:42.847312Z",
    "reviewReply": {
      "comment": "Great to hear the food and service hit the mark. Hope to see you again soon.",
      "updateTime": "2026-03-09T11:26:48.694115Z"
    },
    "name": "accounts/100486096577551952970/locations/7132653567992557892/reviews/Ci9DQUlRQUNvZENodHljRjlvT25FMWJIQm9WamhtUjJoWlRuZERSSFpGUjFkWlJrRRAB"
  }, {
    "reviewer": {
      "displayName": "Vishwanath"
    },
    "starRating": "FIVE",
    "createTime": "2026-03-02T16:33:49.318288Z",
    "updateTime": "2026-03-02T16:33:49.318288Z",
    "name": "accounts/100486096577551952970/locations/7132653567992557892/reviews/Ci9DQUlRQUNvZENodHljRjlvT2xsUk0xWjBVMDlRYjNSSVpWVjJhbXBQU2pSa01IYxAB"
  }, {
    "reviewer": {
      "displayName": "swayambhar majumder"
    },
    "starRating": "FIVE",
    "comment": "We stopped by the cafe during our shopping session!! Pizza was great, felt like fresh like home ! We tried their kenya beans, they were so good we packed some for home !!\n\nMust calls for second visit !!",
    "createTime": "2026-03-02T12:57:17.443623Z",
    "updateTime": "2026-03-02T12:57:17.443623Z",
    "name": "accounts/100486096577551952970/locations/7132653567992557892/reviews/Ci9DQUlRQUNvZENodHljRjlvT21GQ2FuQnJSVGMxYzFCek4zRlJMVFpZYzJONFQzYxAB"
  }, {
    "reviewer": {
      "displayName": "Sheetal Kuril"
    },
    "starRating": "FIVE",
    "comment": "Good food,Good Beverages,Good Service",
    "createTime": "2026-03-01T19:49:03.836543Z",
    "updateTime": "2026-03-01T19:49:03.836543Z",
    "name": "accounts/100486096577551952970/locations/7132653567992557892/reviews/Ci9DQUlRQUNvZENodHljRjlvT210elRVMHhka05IVjA0NFJVVkNaR3ByU2xGWlNXYxAB"
  }, {
    "reviewer": {
      "displayName": "Shaswati Changmai"
    },
    "starRating": "FIVE",
    "createTime": "2026-02-28T17:13:08.638806Z",
    "updateTime": "2026-02-28T17:13:08.638806Z",
    "name": "accounts/100486096577551952970/locations/7132653567992557892/reviews/Ci9DQUlRQUNvZENodHljRjlvT2tOSmExWk9iRGxJTWxkTVdHSmpNVVp4YjB0U1ZYYxAB"
  }, {
    "reviewer": {
      "displayName": "Sakshi Singh"
    },
    "starRating": "FIVE",
    "comment": "Had great coffee after long time and special shout out to Ashish for being the best host",
    "createTime": "2026-02-28T16:51:12.361352Z",
    "updateTime": "2026-02-28T16:55:50.467784Z",
    "name": "accounts/100486096577551952970/locations/7132653567992557892/reviews/Ci9DQUlRQUNvZENodHljRjlvT25WVFNqUTVWMjUzZWxWWE9IWnFTVGxOVTJaRk9IYxAB"
  }, {
    "reviewer": {
      "displayName": "Sonal Singh"
    },
    "starRating": "FIVE",
    "comment": "The staff is really helpful and food is also great",
    "createTime": "2026-02-28T16:50:00.674640Z",
    "updateTime": "2026-02-28T16:50:00.674640Z",
    "name": "accounts/100486096577551952970/locations/7132653567992557892/reviews/Ci9DQUlRQUNvZENodHljRjlvT2s1U1YybEhObU5zYVZodlYzcFRaa295VUdOVmMyYxAB"
  }]
}