{
  "reviews": [{
    "reviewer": {
      "displayName": "Aakash Mane"
    },
    "starRating": "FIVE",
    "comment": "Cold coffee was really so nice and authentic.. also the staff service was good specially karan he was really polite. It was a good experience overall.",
    "createTime": "2026-02-25T14:36:21.645260Z",
    "updateTime": "2026-02-25T14:36:21.645260Z",
    "reviewReply": {
      "comment": "Delighted you enjoyed the cold coffee and the overall experience. Our team will be happy to hear your kind feedback. Looking forward to hosting you again.",
      "updateTime": "2026-03-08T09:38:30.662351Z"
    },
    "name": "accounts/100486096577551952970/locations/10866130483095140789/reviews/Ci9DQUlRQUNvZENodHljRjlvT2tSa1kwVjRMV2czVnpaM1FuSkpkRzFaV2toTVptYxAB"
  }, {
    "reviewer": {
      "displayName": "Divyanshu Rai"
    },
    "starRating": "FIVE",
    "comment": "Love the coffee",
    "createTime": "2026-02-25T07:06:52.750115Z",
    "updateTime": "2026-02-25T07:06:52.750115Z",
    "reviewReply": {
      "comment": "Thank you! We\u0027re so happy you had a great coffee experience. Can’t wait to have you back - there’s always more to discover!",
      "updateTime": "2026-02-25T12:14:42.327326Z"
    },
    "name": "accounts/100486096577551952970/locations/10866130483095140789/reviews/Ci9DQUlRQUNvZENodHljRjlvT25seE5XaDFSRmhtTlZCdlNXOVhVM2RxTm5SNVdXYxAB"
  }, {
    "reviewer": {
      "displayName": "Shashi Yadav"
    },
    "starRating": "FIVE",
    "comment": "Loved the Ambience and food. Coffee was the Iceberg. Beautiful Place",
    "createTime": "2026-02-25T04:18:23.074150Z",
    "updateTime": "2026-02-25T04:18:23.074150Z",
    "reviewReply": {
      "comment": "Great food, lovely ambience, and coffee sounds like a perfect visit. See you again soon for more.",
      "updateTime": "2026-02-25T12:16:11.735170Z"
    },
    "name": "accounts/100486096577551952970/locations/10866130483095140789/reviews/Ci9DQUlRQUNvZENodHljRjlvT2treFYyWlhjVWRhYnpkeWRHY3RhakJSTWxwQmJVRRAB"
  }, {
    "reviewer": {
      "displayName": "Rajendra Kuwalekar"
    },
    "starRating": "FIVE",
    "comment": "The coffee was really good and I like the ambience as well the staff is so kind and helpful\nDo visit there",
    "createTime": "2026-02-24T14:06:16.502458Z",
    "updateTime": "2026-02-24T14:06:16.502458Z",
    "reviewReply": {
      "comment": "Great to know the coffee and ambience stood out, and that our team made you feel welcome. See you again soon.",
      "updateTime": "2026-02-25T12:13:15.774849Z"
    },
    "name": "accounts/100486096577551952970/locations/10866130483095140789/reviews/Ci9DQUlRQUNvZENodHljRjlvT2xadFFXUkliR3BpVEVoTVJrUnBkWEZXVEdwMFVXYxAB"
  }, {
    "reviewer": {
      "displayName": "Vivek Yadav"
    },
    "starRating": "FIVE",
    "comment": "The coffee really nice .\nI have one browni and it\u0027s also really good .\nStaff is so polite",
    "createTime": "2026-02-24T14:02:32.697095Z",
    "updateTime": "2026-02-24T14:02:32.697095Z",
    "reviewReply": {
      "comment": "So glad you enjoyed the coffee and the brownie! Happy to hear our team made the experience even better. Looking forward to your next visit.",
      "updateTime": "2026-02-25T12:12:20.224141Z"
    },
    "name": "accounts/100486096577551952970/locations/10866130483095140789/reviews/Ci9DQUlRQUNvZENodHljRjlvT25aUVdURjVjRGh3ZEVGT1NVUkZRVVIwVGxrMGExRRAB"
  }, {
    "reviewer": {
      "displayName": "Parag Jain"
    },
    "starRating": "FIVE",
    "comment": "Had a lovely experience at Coffee Island! We tried the butter croissant, pistachio cappuccino, and maple pancake with whipped cream — and honestly, everything was absolutely delicious.\n\nThe croissant was perfectly flaky and buttery, just how it should be. The pistachio cappuccino had a rich, nutty flavor without being overpowering — such a unique and well-balanced drink. And the maple pancake with whipped cream - Soft, indulgent, and beautifully authentic.\n\nDefinitely a great spot if you’re looking for quality coffee and desserts done right. Will be coming back!",
    "createTime": "2026-02-22T14:18:20.891368Z",
    "updateTime": "2026-02-22T14:18:20.891368Z",
    "reviewReply": {
      "comment": "So glad you enjoyed the croissant, pistachio cappuccino, and maple pancake - a combination we love too. Happy to hear everything hit the mark. See you again soon for more great coffee and desserts.",
      "updateTime": "2026-03-08T09:36:10.416808Z"
    },
    "name": "accounts/100486096577551952970/locations/10866130483095140789/reviews/Ci9DQUlRQUNvZENodHljRjlvT2xGMU5VcG9VazQxY25wRVFtTXhOVlprYTJGcFYyYxAB"
  }, {
    "reviewer": {
      "displayName": "Eepshita Das"
    },
    "starRating": "FIVE",
    "comment": "Hot pistachio and mocha coffee was the best. Must give it a try.",
    "createTime": "2026-02-19T17:22:51.734433Z",
    "updateTime": "2026-02-19T17:22:51.734433Z",
    "reviewReply": {
      "comment": "Thank you! We\u0027re so happy you had a great coffee experience. Can’t wait to have you back - there’s always more to discover!",
      "updateTime": "2026-02-24T10:52:03.655301Z"
    },
    "name": "accounts/100486096577551952970/locations/10866130483095140789/reviews/Ci9DQUlRQUNvZENodHljRjlvT25NNU1EZFphV3R5VVV0aWExbDVOMjFmTUZaVFRrRRAB"
  }, {
    "reviewer": {
      "displayName": "Parag Katre"
    },
    "starRating": "FIVE",
    "comment": "Good Ambience and food",
    "createTime": "2026-02-19T17:22:42.126671Z",
    "updateTime": "2026-02-19T17:22:42.126671Z",
    "reviewReply": {
      "comment": "So glad you enjoyed the ambience and food, that’s exactly the vibe we love creating.Looking forward to welcoming you back for more great moments soon! ☕ ",
      "updateTime": "2026-02-24T10:54:02.615805Z"
    },
    "name": "accounts/100486096577551952970/locations/10866130483095140789/reviews/Ci9DQUlRQUNvZENodHljRjlvT2xaNGVXNVhkMVEyVnpsdlpGaFFVMFpqY1RsV2QzYxAB"
  }, {
    "reviewer": {
      "displayName": "Rashmi Nikam"
    },
    "starRating": "FIVE",
    "comment": "Good food good ambience",
    "createTime": "2026-02-19T17:22:37.605190Z",
    "updateTime": "2026-02-19T17:22:37.605190Z",
    "reviewReply": {
      "comment": "So glad you enjoyed the ambience and food, that’s exactly the vibe we love creating.Looking forward to welcoming you back for more great moments soon! ☕",
      "updateTime": "2026-02-24T10:54:23.227484Z"
    },
    "name": "accounts/100486096577551952970/locations/10866130483095140789/reviews/Ci9DQUlRQUNvZENodHljRjlvT2xoQk16QkpTRTlNYVZWYVNGQnVkSGRWWXpSbk1IYxAB"
  }, {
    "reviewer": {
      "displayName": "Abhijit Kar"
    },
    "starRating": "FIVE",
    "comment": "Excellent ambience and great coffee!",
    "createTime": "2026-02-19T10:34:43.288010Z",
    "updateTime": "2026-02-19T10:34:43.288010Z",
    "reviewReply": {
      "comment": "Thank you! We\u0027re so happy you had a great coffee experience. Can’t wait to have you back - there’s always more to discover!",
      "updateTime": "2026-02-24T10:52:10.975757Z"
    },
    "name": "accounts/100486096577551952970/locations/10866130483095140789/reviews/Ci9DQUlRQUNvZENodHljRjlvT25KWWIzRm9SMU5rWW1wSFRGOVdVazV1VVZSb2VYYxAB"
  }, {
    "reviewer": {
      "displayName": "ronnii k"
    },
    "starRating": "FIVE",
    "comment": "Really beautiful café, Had a feeling of french breakfast 👌🏻",
    "createTime": "2026-02-19T07:18:00.171089Z",
    "updateTime": "2026-02-19T07:18:00.171089Z",
    "reviewReply": {
      "comment": "Thank you! So glad you loved the European coffee experience right where you\u0027re at. We’ll keep the brews bold and the vibes just right, see you again soon!",
      "updateTime": "2026-02-24T10:56:40.660514Z"
    },
    "name": "accounts/100486096577551952970/locations/10866130483095140789/reviews/Ci9DQUlRQUNvZENodHljRjlvT25WaE1YVjRXVEJ3WVc5VE9GbzViMngxU1VoV1gzYxAB"
  }, {
    "reviewer": {
      "displayName": "Aditi Srivastava"
    },
    "starRating": "FOUR",
    "comment": "Beverages are nice, got good suggestion from Tanmay for them. We had Zesty Mango and Berry blast which were very refreshing. Nachos were average.\nThough I enjoy the overall spacious and youthful atmostphere of the cafe.",
    "createTime": "2026-02-18T16:33:44.728337Z",
    "updateTime": "2026-02-18T16:33:44.728337Z",
    "reviewReply": {
      "comment": "Great to know the drinks were refreshing and the atmosphere felt just right. Your feedback on the nachos has been noted as we’re continuously working on elevating every bite. See you again soon.",
      "updateTime": "2026-02-24T10:58:03.655292Z"
    },
    "name": "accounts/100486096577551952970/locations/10866130483095140789/reviews/Ci9DQUlRQUNvZENodHljRjlvT25RMVlXMHlPRVIzVVZSSlFVVmhVREkxTmxOWFoxRRAB"
  }, {
    "reviewer": {
      "displayName": "Avni Nair"
    },
    "starRating": "FIVE",
    "createTime": "2026-02-18T16:32:29.024961Z",
    "updateTime": "2026-02-18T16:32:29.024961Z",
    "reviewReply": {
      "comment": "Thanks a latte for the 5 stars! Your support keeps us brewing our best every day.",
      "updateTime": "2026-02-24T10:49:27.706488Z"
    },
    "name": "accounts/100486096577551952970/locations/10866130483095140789/reviews/Ci9DQUlRQUNvZENodHljRjlvT2tNNWVUWmtNbWRuUWtoWVZUUlhTbDl1UVRKQ1lYYxAB"
  }, {
    "reviewer": {
      "displayName": "Anushka Dubey"
    },
    "starRating": "FOUR",
    "comment": "Can widen the menu.",
    "createTime": "2026-02-18T16:25:46.275250Z",
    "updateTime": "2026-02-18T16:25:46.275250Z",
    "reviewReply": {
      "comment": "We’re glad you had a good experience, and we appreciate the suggestion. Expanding and refining the menu is something we’re always working on as we continue to evolve our offerings. Hope to welcome you back again soon.",
      "updateTime": "2026-03-10T10:00:50.132107Z"
    },
    "name": "accounts/100486096577551952970/locations/10866130483095140789/reviews/Ci9DQUlRQUNvZENodHljRjlvT25KUFduaE9NWFE1ZUVveVZqQkxUMHRNYURJdFVYYxAB"
  }, {
    "reviewer": {
      "displayName": "Rukmani Hegde"
    },
    "starRating": "FIVE",
    "comment": "Liked the avo toast and chicken bolognaise",
    "createTime": "2026-02-18T13:00:53.957914Z",
    "updateTime": "2026-02-18T13:00:53.957914Z",
    "reviewReply": {
      "comment": "So glad you enjoyed the food, that’s what we love to hear!Looking forward to serving you again soon. ",
      "updateTime": "2026-02-24T10:59:41.052561Z"
    },
    "name": "accounts/100486096577551952970/locations/10866130483095140789/reviews/Ci9DQUlRQUNvZENodHljRjlvT2xKRUxXUmZkamROVXpsU1ZEWXhRM0J1TUZCUVRHYxAB"
  }, {
    "reviewer": {
      "displayName": "sonal shrivastava"
    },
    "starRating": "FIVE",
    "comment": "Good Ambience\nGood coffee\nBarister Yuvraj guided us well for some nice brews",
    "createTime": "2026-02-16T14:04:17.618471Z",
    "updateTime": "2026-02-16T14:04:17.618471Z",
    "reviewReply": {
      "comment": "We’re so glad you enjoyed the ambience and the coffee! It’s wonderful to hear that our barista could guide you through some great brews. That’s exactly the kind of European coffee experience we love creating. Looking forward to your next visit ☕",
      "updateTime": "2026-02-17T10:32:35.120006Z"
    },
    "name": "accounts/100486096577551952970/locations/10866130483095140789/reviews/Ci9DQUlRQUNvZENodHljRjlvT2pGamNGaG5VRkZSVG10RVUwbHhNQzFTU0d4U2NGRRAB"
  }, {
    "reviewer": {
      "displayName": "Anjum Farishta"
    },
    "starRating": "FOUR",
    "createTime": "2026-02-16T14:02:25.037228Z",
    "updateTime": "2026-02-16T14:02:25.037228Z",
    "reviewReply": {
      "comment": "Great to know you had a good experience. We’re working every day to elevate every cup and every bite, hope to welcome you back soon.",
      "updateTime": "2026-02-24T11:00:47.036249Z"
    },
    "name": "accounts/100486096577551952970/locations/10866130483095140789/reviews/Ci9DQUlRQUNvZENodHljRjlvT2t0UlEyNWpZblJWZG1obFFVaEdaVmxoV1VGQkxWRRAB"
  }, {
    "reviewer": {
      "displayName": "lijisri prabhakaran"
    },
    "starRating": "FOUR",
    "comment": "Awesome brews.. nice place to hang out.",
    "createTime": "2026-02-16T14:00:12.761228Z",
    "updateTime": "2026-02-16T14:00:12.761228Z",
    "reviewReply": {
      "comment": "Great to know you had a good experience. We’re working every day to elevate every cup and every bite — hope to welcome you back soon.",
      "updateTime": "2026-02-24T11:01:01.937967Z"
    },
    "name": "accounts/100486096577551952970/locations/10866130483095140789/reviews/Ci9DQUlRQUNvZENodHljRjlvT2xZdE9EaHJibkZVTUdOSVprdFJlRXBZYkVwbE4zYxAB"
  }, {
    "reviewer": {
      "displayName": "Farzan Khan"
    },
    "starRating": "FIVE",
    "comment": "God food",
    "createTime": "2026-02-14T05:35:07.809473Z",
    "updateTime": "2026-02-14T05:35:07.809473Z",
    "reviewReply": {
      "comment": "Thanks a latte for the 5 stars! Your support keeps us brewing our best every day.",
      "updateTime": "2026-02-24T10:50:29.650929Z"
    },
    "name": "accounts/100486096577551952970/locations/10866130483095140789/reviews/Ci9DQUlRQUNvZENodHljRjlvT2tOMWJIQjVPVmx0Vms1eGNpMTBhRVE1VVVWb05rRRAB"
  }, {
    "reviewer": {
      "displayName": "Erick"
    },
    "starRating": "FIVE",
    "comment": "Good coffee",
    "createTime": "2026-02-13T13:07:42.649485Z",
    "updateTime": "2026-02-13T13:07:42.649485Z",
    "reviewReply": {
      "comment": "Thanks a latte for the 5 stars! Your support keeps us brewing our best every day.",
      "updateTime": "2026-02-24T10:50:24.872764Z"
    },
    "name": "accounts/100486096577551952970/locations/10866130483095140789/reviews/Ci9DQUlRQUNvZENodHljRjlvT21wS05XdExVR2xZV0hwa2F5MUhTR05RT1Zwd1IwRRAB"
  }]
}